{
    "Id":  "0a7724eb-e74f-408a-833e-4872b15f0e07",
    "Title":  "每週採購 - 頂好 (01/21)",
    "CreatedAt":  "2025-01-19T05:45:42.635133+08:00",
    "Items":  [
                  {
                      "Id":  "c7030573-df04-4f8b-9f1d-4f9b154454d2",
                      "Name":  "廚房清潔劑",
                      "Quantity":  1,
                      "Price":  54,
                      "IsCompleted":  false,
                      "CreatedAt":  "2025-01-20T05:54:25.7846399+08:00",
                      "CompletedAt":  null
                  },
                  {
                      "Id":  "9a1c758d-e627-49ad-9c96-7e0a1bdbc61c",
                      "Name":  "氣泡水",
                      "Quantity":  3,
                      "Price":  129,
                      "IsCompleted":  false,
                      "CreatedAt":  "2025-01-15T06:57:51.7250576+08:00",
                      "CompletedAt":  null
                  },
                  {
                      "Id":  "8d3b8555-1bce-4e01-a17a-92b9c3763316",
                      "Name":  "黑巧克力",
                      "Quantity":  3,
                      "Price":  118,
                      "IsCompleted":  false,
                      "CreatedAt":  "2025-01-15T06:01:28.2949455+08:00",
                      "CompletedAt":  null
                  },
                  {
                      "Id":  "65532054-ea19-45ec-8609-07ee35a8b2f1",
                      "Name":  "木質相框",
                      "Quantity":  1,
                      "Price":  31,
                      "IsCompleted":  false,
                      "CreatedAt":  "2025-01-19T17:36:00.716369+08:00",
                      "CompletedAt":  null
                  },
                  {
                      "Id":  "58f5b833-0a0e-4372-acdf-ee66307b8fc8",
                      "Name":  "電動牙刷",
                      "Quantity":  3,
                      "Price":  192,
                      "IsCompleted":  false,
                      "CreatedAt":  "2025-01-16T16:19:16.8001948+08:00",
                      "CompletedAt":  null
                  }
              ],
    "BuyData":  "2024-01/21"
}
