{
    "Id":  "0c48e8cf-6bbb-4c4c-9059-af0c3111d8ce",
    "Title":  "01/15 ­¹«~ÁÊª«²M³æ",
    "CreatedAt":  "2025-01-18T22:33:00.385782+08:00",
    "Items":  [
                  {
                      "Id":  "c3f1b601-ea59-4593-b698-291e9ed109ec",
                      "Name":  "Unbranded Cotton Bacon",
                      "Quantity":  2,
                      "Price":  458,
                      "IsCompleted":  true,
                      "CreatedAt":  "2025-01-21T13:26:51.5115321Z",
                      "CompletedAt":  null
                  },
                  {
                      "Id":  "fd11d0f7-bffb-48a5-95d0-d848ccd00655",
                      "Name":  "½Õ¨ý®Æ",
                      "Quantity":  5,
                      "Price":  322,
                      "IsCompleted":  true,
                      "CreatedAt":  "2025-01-21T13:26:51.5115399Z",
                      "CompletedAt":  null
                  },
                  {
                      "Id":  "4f7bce93-f3c9-484e-827e-3293642bee4d",
                      "Name":  "ªÎ¨m",
                      "Quantity":  1,
                      "Price":  242,
                      "IsCompleted":  false,
                      "CreatedAt":  "2025-01-21T13:26:51.5115412Z",
                      "CompletedAt":  null
                  },
                  {
                      "Id":  "54146fce-71fe-4f11-b710-5a9672f0665b",
                      "Name":  "»æ°®",
                      "Quantity":  4,
                      "Price":  292,
                      "IsCompleted":  true,
                      "CreatedAt":  "2025-01-21T13:26:51.5115423Z",
                      "CompletedAt":  null
                  },
                  {
                      "Id":  "89b50bd1-86ef-4f06-9914-95274a204b73",
                      "Name":  "¬~¦ç¯»",
                      "Quantity":  4,
                      "Price":  348,
                      "IsCompleted":  false,
                      "CreatedAt":  "2025-01-21T13:26:51.5115433Z",
                      "CompletedAt":  null
                  },
                  {
                      "Id":  "a86143ab-5dc8-4d32-9f0d-bad0d5a52557",
                      "Name":  "ªÎ¨m",
                      "Quantity":  4,
                      "Price":  40,
                      "IsCompleted":  true,
                      "CreatedAt":  "2025-01-21T13:26:51.5115466Z",
                      "CompletedAt":  null
                  },
                  {
                      "Id":  "6bc6d3fd-99e8-46a2-acfb-d2074a8f85de",
                      "Name":  "¶¼®Æ",
                      "Quantity":  3,
                      "Price":  483,
                      "IsCompleted":  true,
                      "CreatedAt":  "2025-01-21T13:26:51.5115477Z",
                      "CompletedAt":  null
                  },
                  {
                      "Id":  "0b9b967f-6e7a-474b-9047-badd6ca8ac49",
                      "Name":  "Tasty Steel Chicken",
                      "Quantity":  3,
                      "Price":  42,
                      "IsCompleted":  false,
                      "CreatedAt":  "2025-01-21T13:26:51.5115563Z",
                      "CompletedAt":  null
                  },
                  {
                      "Id":  "150c551c-2407-44b9-ba16-307a082973af",
                      "Name":  "³½",
                      "Quantity":  5,
                      "Price":  59,
                      "IsCompleted":  false,
                      "CreatedAt":  "2025-01-21T13:26:51.5115574Z",
                      "CompletedAt":  null
                  }
              ],
    "BuyData":  "2024-01/15"
}
