{
    "Id":  "275488ff-94e1-492f-8253-7060c2aba7a9",
    "Title":  "聚會準備 - 愛買 (01/21)",
    "CreatedAt":  "2025-01-21T13:46:40.7431943+08:00",
    "Items":  [
                  {
                      "Id":  "f6ac056d-6664-41d2-93f4-d2a1200cccb0",
                      "Name":  "靜電掃把",
                      "Quantity":  5,
                      "Price":  210,
                      "IsCompleted":  false,
                      "CreatedAt":  "2025-01-20T15:58:39.7747206+08:00",
                      "CompletedAt":  null
                  },
                  {
                      "Id":  "8af2e4f6-37c1-4f69-a2a8-ff09a6d54569",
                      "Name":  "食品級保鮮膜",
                      "Quantity":  5,
                      "Price":  50,
                      "IsCompleted":  true,
                      "CreatedAt":  "2025-01-15T12:56:10.1150284+08:00",
                      "CompletedAt":  "2025-01-16T03:54:47.4053825+08:00"
                  },
                  {
                      "Id":  "aecf0017-f894-4ef5-be73-15d71e30b587",
                      "Name":  "中性筆組",
                      "Quantity":  2,
                      "Price":  37,
                      "IsCompleted":  false,
                      "CreatedAt":  "2025-01-15T03:03:49.0386878+08:00",
                      "CompletedAt":  null
                  },
                  {
                      "Id":  "73e003ad-98d9-4a52-b6de-e56b1c9c2be3",
                      "Name":  "有機番茄",
                      "Quantity":  5,
                      "Price":  254,
                      "IsCompleted":  false,
                      "CreatedAt":  "2025-01-15T04:54:31.5887225+08:00",
                      "CompletedAt":  null
                  },
                  {
                      "Id":  "e5fcdd98-117c-4ea7-a4b0-1e6cbc4d97f5",
                      "Name":  "鮮榨果汁",
                      "Quantity":  5,
                      "Price":  178,
                      "IsCompleted":  false,
                      "CreatedAt":  "2025-01-21T01:29:03.1226237+08:00",
                      "CompletedAt":  null
                  },
                  {
                      "Id":  "b68c3cd3-7a98-4ae8-8f34-ab892f6c8981",
                      "Name":  "透明膠帶",
                      "Quantity":  1,
                      "Price":  117,
                      "IsCompleted":  false,
                      "CreatedAt":  "2025-01-15T21:21:02.7923811+08:00",
                      "CompletedAt":  null
                  }
              ],
    "BuyData":  "2024-01/21"
}
