{
    "Id":  "3c2525c3-4de4-4d7a-845e-05b157c3dbb5",
    "Title":  "01/17 個人護理採買清單",
    "CreatedAt":  "2025-01-17T21:26:48.9073508+08:00",
    "Items":  [
                  {
                      "Id":  "a8d89e39-b7d7-40d6-be06-60ab50fb2bc5",
                      "Name":  "麵條",
                      "Quantity":  1,
                      "Price":  80,
                      "IsCompleted":  true,
                      "CreatedAt":  "2025-01-21T13:16:36.9571437Z",
                      "CompletedAt":  null
                  },
                  {
                      "Id":  "fc95de53-9e9f-44e4-87cc-e0cf34d67d1a",
                      "Name":  "飲料",
                      "Quantity":  3,
                      "Price":  273,
                      "IsCompleted":  true,
                      "CreatedAt":  "2025-01-21T13:16:36.9571519Z",
                      "CompletedAt":  null
                  },
                  {
                      "Id":  "d8b67f44-c010-4a19-a257-731cab6b910b",
                      "Name":  "調味料",
                      "Quantity":  3,
                      "Price":  319,
                      "IsCompleted":  false,
                      "CreatedAt":  "2025-01-21T13:16:36.9571536Z",
                      "CompletedAt":  null
                  },
                  {
                      "Id":  "3b3807a5-8c5b-4fee-b794-7ed0467b86e9",
                      "Name":  "蘋果",
                      "Quantity":  3,
                      "Price":  407,
                      "IsCompleted":  true,
                      "CreatedAt":  "2025-01-21T13:16:36.9571551Z",
                      "CompletedAt":  null
                  },
                  {
                      "Id":  "d2b24ce8-0e04-4365-9818-1fb98ef42430",
                      "Name":  "牙膏",
                      "Quantity":  5,
                      "Price":  98,
                      "IsCompleted":  false,
                      "CreatedAt":  "2025-01-21T13:16:36.9571567Z",
                      "CompletedAt":  null
                  }
              ],
    "BuyData":  "2024-01/17"
}
