{
    "Id":  "68af16f0-6947-4c86-b56b-9eee34acd2e0",
    "Title":  "01/18 生鮮購物清單",
    "CreatedAt":  "2025-01-20T17:15:17.0418066+08:00",
    "Items":  [
                  {
                      "Id":  "7eed1c2b-da95-4e55-8d37-9befb6504dd7",
                      "Name":  "罐頭",
                      "Quantity":  1,
                      "Price":  390,
                      "IsCompleted":  false,
                      "CreatedAt":  "2025-01-21T19:08:56.7640023Z",
                      "CompletedAt":  null
                  },
                  {
                      "Id":  "82265009-ed93-4a1e-947e-e811b6835004",
                      "Name":  "垃圾袋",
                      "Quantity":  3,
                      "Price":  102,
                      "IsCompleted":  false,
                      "CreatedAt":  "2025-01-21T19:08:56.7640046Z",
                      "CompletedAt":  null
                  },
                  {
                      "Id":  "2e0a4f41-a3ac-46ea-a325-3d4d282f06c1",
                      "Name":  "鹽",
                      "Quantity":  4,
                      "Price":  117,
                      "IsCompleted":  true,
                      "CreatedAt":  "2025-01-21T19:08:56.7640069Z",
                      "CompletedAt":  null
                  },
                  {
                      "Id":  "f9ba1103-72f5-4643-82fb-e78422c36502",
                      "Name":  "魚",
                      "Quantity":  2,
                      "Price":  444,
                      "IsCompleted":  false,
                      "CreatedAt":  "2025-01-21T19:08:56.7640077Z",
                      "CompletedAt":  null
                  },
                  {
                      "Id":  "6b2cf74e-7931-40de-b070-ab083b2f295e",
                      "Name":  "香蕉",
                      "Quantity":  2,
                      "Price":  388,
                      "IsCompleted":  false,
                      "CreatedAt":  "2025-01-21T19:08:56.7640087Z",
                      "CompletedAt":  null
                  },
                  {
                      "Id":  "9c35e113-47c9-4fca-aef7-d85e7c8dcab9",
                      "Name":  "蘋果",
                      "Quantity":  1,
                      "Price":  76,
                      "IsCompleted":  false,
                      "CreatedAt":  "2025-01-21T19:08:56.7640106Z",
                      "CompletedAt":  null
                  },
                  {
                      "Id":  "4caf1641-3172-48ec-858a-0144bd6c1030",
                      "Name":  "洗髮精",
                      "Quantity":  2,
                      "Price":  253,
                      "IsCompleted":  false,
                      "CreatedAt":  "2025-01-21T19:08:56.7640117Z",
                      "CompletedAt":  null
                  },
                  {
                      "Id":  "5c27f0ac-2af7-4000-9034-120e696c0f9a",
                      "Name":  "果汁",
                      "Quantity":  4,
                      "Price":  57,
                      "IsCompleted":  true,
                      "CreatedAt":  "2025-01-21T19:08:56.7640128Z",
                      "CompletedAt":  null
                  }
              ],
    "BuyData":  "2024-01/18"
}
