{
    "Id":  "84c1bfa8-2e11-4fff-80a1-77fb2910d1b4",
    "Title":  "01/21 日常用品採買清單",
    "CreatedAt":  "2025-01-21T08:19:52.9697018+08:00",
    "Items":  [
                  {
                      "Id":  "10962ac2-311e-4a87-afd7-e81c5ac1bbda",
                      "Name":  "洗髮精",
                      "Quantity":  3,
                      "Price":  271,
                      "IsCompleted":  false,
                      "CreatedAt":  "2025-01-21T14:07:30.5540644Z",
                      "CompletedAt":  null
                  },
                  {
                      "Id":  "88f849b1-6f21-404b-8d23-232773d1fa7c",
                      "Name":  "茶",
                      "Quantity":  1,
                      "Price":  61,
                      "IsCompleted":  true,
                      "CreatedAt":  "2025-01-21T14:07:30.5540679Z",
                      "CompletedAt":  null
                  },
                  {
                      "Id":  "6357838f-a929-4bd8-a0b1-2d8d655dd1b8",
                      "Name":  "蔬菜",
                      "Quantity":  2,
                      "Price":  152,
                      "IsCompleted":  false,
                      "CreatedAt":  "2025-01-21T14:07:30.5540708Z",
                      "CompletedAt":  null
                  }
              ],
    "BuyData":  "2024-01/21"
}
