{
    "Id":  "93a565ce-879f-4748-aa7f-6a41859d5937",
    "Title":  "»E·|±ÄÁÊ - 01/21",
    "CreatedAt":  "2025-01-21T09:32:53.640454+08:00",
    "Items":  [
                  {
                      "Id":  "c6ef42fb-1c6a-413d-9a25-4b5ed993f968",
                      "Name":  "ªwÄÑ",
                      "Quantity":  2,
                      "Price":  383.315386859563610,
                      "IsCompleted":  false,
                      "CreatedAt":  "2025-01-15T07:44:40.7629976+08:00",
                      "CompletedAt":  null
                  },
                  {
                      "Id":  "d60931d1-8e8a-40b1-bd5e-f2e5c6dfc907",
                      "Name":  "ªÚ­»¾¯",
                      "Quantity":  5,
                      "Price":  482.395565790495410,
                      "IsCompleted":  false,
                      "CreatedAt":  "2025-01-21T13:42:08.5901193+08:00",
                      "CompletedAt":  null
                  },
                  {
                      "Id":  "2c76c1cd-1458-450a-96b8-58fe022c4436",
                      "Name":  "½L¤l",
                      "Quantity":  5,
                      "Price":  100.814124542815380,
                      "IsCompleted":  false,
                      "CreatedAt":  "2025-01-17T08:23:09.7333079+08:00",
                      "CompletedAt":  null
                  },
                  {
                      "Id":  "f21dadcd-c0cd-42a3-bce5-83ef67acbb78",
                      "Name":  "©Ù¥¬",
                      "Quantity":  1,
                      "Price":  371.953583266448740,
                      "IsCompleted":  false,
                      "CreatedAt":  "2025-01-20T00:33:24.8204612+08:00",
                      "CompletedAt":  null
                  },
                  {
                      "Id":  "305308cf-04fc-45c9-901a-808f568aa4ae",
                      "Name":  "´Ö³Q",
                      "Quantity":  1,
                      "Price":  147.886803788372660,
                      "IsCompleted":  false,
                      "CreatedAt":  "2025-01-17T15:17:50.1849002+08:00",
                      "CompletedAt":  null
                  },
                  {
                      "Id":  "8f029ee0-0e10-49b6-ae61-1544a66ca2d5",
                      "Name":  "ªM¤l",
                      "Quantity":  5,
                      "Price":  10.84155737200870440,
                      "IsCompleted":  true,
                      "CreatedAt":  "2025-01-21T15:31:38.714017+08:00",
                      "CompletedAt":  "2025-01-22T19:05:32.9481594+08:00"
                  }
              ],
    "BuyData":  "2024-01/21"
}
