{
    "Id":  "94dcc560-600e-4189-80c6-84b4008c9370",
    "Title":  "派對用品 - 夜市 (01/20)",
    "CreatedAt":  "2025-01-18T12:03:04.6391604+08:00",
    "Items":  [
                  {
                      "Id":  "3880c749-b304-4d3f-ac66-74899d2438ae",
                      "Name":  "手工蛋糕",
                      "Quantity":  2,
                      "Price":  101,
                      "IsCompleted":  true,
                      "CreatedAt":  "2025-01-17T19:25:56.190879+08:00",
                      "CompletedAt":  "2025-01-18T00:23:36.6423587+08:00"
                  },
                  {
                      "Id":  "b5a7e3f2-4bf7-4dbf-a514-8eeb661cc8fa",
                      "Name":  "手工蛋糕",
                      "Quantity":  3,
                      "Price":  154,
                      "IsCompleted":  true,
                      "CreatedAt":  "2025-01-19T10:23:56.3515145+08:00",
                      "CompletedAt":  "2025-01-19T22:10:51.9211508+08:00"
                  },
                  {
                      "Id":  "0f895567-c1e2-4535-8cfb-78438b0ecf48",
                      "Name":  "金屬直尺",
                      "Quantity":  2,
                      "Price":  38,
                      "IsCompleted":  false,
                      "CreatedAt":  "2025-01-17T18:03:51.3959313+08:00",
                      "CompletedAt":  null
                  }
              ],
    "BuyData":  "2024-01/20"
}
