{
    "Id":  "a54c9c8c-db2e-4b3a-b796-02cea823c331",
    "Title":  "01/19 ¤é±`¥Î«~ÁÊª«²M³æ",
    "CreatedAt":  "2025-01-15T04:21:27.967684+08:00",
    "Items":  [
                  {
                      "Id":  "2cf23f9e-4f44-46d1-ac60-861a85cd3ac9",
                      "Name":  "¤ú»I",
                      "Quantity":  1,
                      "Price":  336,
                      "IsCompleted":  false,
                      "CreatedAt":  "2025-01-21T14:26:57.1686718Z",
                      "CompletedAt":  null
                  },
                  {
                      "Id":  "bff18857-2e53-4df6-987f-4b4ca30297f9",
                      "Name":  "³J",
                      "Quantity":  1,
                      "Price":  271,
                      "IsCompleted":  true,
                      "CreatedAt":  "2025-01-21T14:26:57.1686745Z",
                      "CompletedAt":  null
                  },
                  {
                      "Id":  "fe2d31ad-eb92-435f-b1ff-9fd2a58e80ea",
                      "Name":  "ÆQ",
                      "Quantity":  5,
                      "Price":  456,
                      "IsCompleted":  true,
                      "CreatedAt":  "2025-01-21T14:26:57.1686773Z",
                      "CompletedAt":  null
                  },
                  {
                      "Id":  "b94281a8-7c3c-4aaf-a2c9-af42b8ffc2f3",
                      "Name":  "¬~¦ç¯»",
                      "Quantity":  1,
                      "Price":  130,
                      "IsCompleted":  true,
                      "CreatedAt":  "2025-01-21T14:26:57.1686783Z",
                      "CompletedAt":  null
                  },
                  {
                      "Id":  "a1fc1bd8-43ba-4d5f-b6bb-900162b47ff7",
                      "Name":  "¦×",
                      "Quantity":  1,
                      "Price":  488,
                      "IsCompleted":  false,
                      "CreatedAt":  "2025-01-21T14:26:57.1686793Z",
                      "CompletedAt":  null
                  },
                  {
                      "Id":  "528f77c0-7a75-4dd4-bca6-936dcfee5a8c",
                      "Name":  "¨N¯D¨Å",
                      "Quantity":  1,
                      "Price":  209,
                      "IsCompleted":  false,
                      "CreatedAt":  "2025-01-21T14:26:57.1686817Z",
                      "CompletedAt":  null
                  },
                  {
                      "Id":  "79a4f20e-cd6b-448e-9fb3-5175c2cc4f57",
                      "Name":  "¬~¦ç¯»",
                      "Quantity":  3,
                      "Price":  117,
                      "IsCompleted":  false,
                      "CreatedAt":  "2025-01-21T14:26:57.1686831Z",
                      "CompletedAt":  null
                  },
                  {
                      "Id":  "543c2978-9ebb-413f-977a-c9b386d754ea",
                      "Name":  "Ä«ªG",
                      "Quantity":  5,
                      "Price":  24,
                      "IsCompleted":  false,
                      "CreatedAt":  "2025-01-21T14:26:57.1686841Z",
                      "CompletedAt":  null
                  }
              ],
    "BuyData":  "2024-01/19"
}
