{
    "Id":  "bdda9318-5cdb-4686-9080-eba71a53a151",
    "Title":  "01/17 清潔用品購物清單",
    "CreatedAt":  "2025-01-21T15:45:24.527137+08:00",
    "Items":  [
                  {
                      "Id":  "72e61a5c-bd5a-427f-8b00-bb25c5981fcb",
                      "Name":  "Unbranded Concrete Car",
                      "Quantity":  1,
                      "Price":  140,
                      "IsCompleted":  true,
                      "CreatedAt":  "2025-01-21T14:07:30.8108338Z",
                      "CompletedAt":  null
                  },
                  {
                      "Id":  "d4c94174-a315-4d6b-b473-637718ea58ff",
                      "Name":  "洗衣粉",
                      "Quantity":  4,
                      "Price":  165,
                      "IsCompleted":  true,
                      "CreatedAt":  "2025-01-21T14:07:30.8108421Z",
                      "CompletedAt":  null
                  },
                  {
                      "Id":  "f61f2810-e6d8-4502-98e1-2b512910b5d8",
                      "Name":  "魚",
                      "Quantity":  3,
                      "Price":  420,
                      "IsCompleted":  false,
                      "CreatedAt":  "2025-01-21T14:07:30.810845Z",
                      "CompletedAt":  null
                  },
                  {
                      "Id":  "8abe92de-7dc7-487b-8111-7ac372738046",
                      "Name":  "零食",
                      "Quantity":  2,
                      "Price":  70,
                      "IsCompleted":  false,
                      "CreatedAt":  "2025-01-21T14:07:30.810848Z",
                      "CompletedAt":  null
                  },
                  {
                      "Id":  "c93068e5-852a-4688-a9ee-8d7fa8355636",
                      "Name":  "Ergonomic Concrete Soap",
                      "Quantity":  2,
                      "Price":  256,
                      "IsCompleted":  true,
                      "CreatedAt":  "2025-01-21T14:07:30.8108558Z",
                      "CompletedAt":  null
                  }
              ],
    "BuyData":  "2024-01/17"
}
