{
    "Id":  "bf7f62c6-fbe1-46dc-8364-e3d676a8ff60",
    "Title":  "派對用品 - 大潤發 (01/21)",
    "CreatedAt":  "2025-01-21T14:50:30.8764822+08:00",
    "Items":  [
                  {
                      "Id":  "afc13470-9d7a-4d3e-add5-b49c80afa49e",
                      "Name":  "靜電掃把",
                      "Quantity":  3,
                      "Price":  194,
                      "IsCompleted":  false,
                      "CreatedAt":  "2025-01-21T06:51:53.5727222+08:00",
                      "CompletedAt":  null
                  },
                  {
                      "Id":  "7f950545-d57d-4f92-a30d-a3ce49642ba8",
                      "Name":  "放牧蛋",
                      "Quantity":  1,
                      "Price":  192,
                      "IsCompleted":  false,
                      "CreatedAt":  "2025-01-15T08:06:33.4476609+08:00",
                      "CompletedAt":  null
                  },
                  {
                      "Id":  "11b809ed-8e5c-4f12-ac19-e04bda08cb3c",
                      "Name":  "天然沐浴乳",
                      "Quantity":  1,
                      "Price":  135,
                      "IsCompleted":  true,
                      "CreatedAt":  "2025-01-19T10:09:33.1091351+08:00",
                      "CompletedAt":  "2025-01-20T05:12:45.8314975+08:00"
                  },
                  {
                      "Id":  "80eaf92f-9edc-4ba1-abe9-ca3320f73e4d",
                      "Name":  "進口可樂",
                      "Quantity":  2,
                      "Price":  31,
                      "IsCompleted":  false,
                      "CreatedAt":  "2025-01-17T02:50:30.4403742+08:00",
                      "CompletedAt":  null
                  },
                  {
                      "Id":  "9cefc2ca-27e5-42d5-9a6e-97c1745f2395",
                      "Name":  "靜電掃把",
                      "Quantity":  3,
                      "Price":  48,
                      "IsCompleted":  true,
                      "CreatedAt":  "2025-01-16T09:00:36.8315301+08:00",
                      "CompletedAt":  "2025-01-16T17:08:56.8323401+08:00"
                  },
                  {
                      "Id":  "7fdc5200-b191-49bb-8f62-1fa8fd00332e",
                      "Name":  "精釀啤酒",
                      "Quantity":  4,
                      "Price":  31,
                      "IsCompleted":  false,
                      "CreatedAt":  "2025-01-15T11:02:10.0927182+08:00",
                      "CompletedAt":  null
                  },
                  {
                      "Id":  "48e091e5-3d91-42df-a7a8-17f2e1852c7b",
                      "Name":  "木質相框",
                      "Quantity":  5,
                      "Price":  21,
                      "IsCompleted":  false,
                      "CreatedAt":  "2025-01-19T14:33:54.0166438+08:00",
                      "CompletedAt":  null
                  }
              ],
    "BuyData":  "2024-01/21"
}
