{
    "Id":  "cd351402-0f00-4da4-8037-8233769c8e67",
    "Title":  "01/20 日常用品購物清單",
    "CreatedAt":  "2025-01-14T20:50:46.4048517+08:00",
    "Items":  [
                  {
                      "Id":  "52cc7765-f9ab-4fa5-ae02-7050d07aa41b",
                      "Name":  "麵包",
                      "Quantity":  2,
                      "Price":  271,
                      "IsCompleted":  false,
                      "CreatedAt":  "2025-01-21T12:49:26.6301287Z",
                      "CompletedAt":  null
                  },
                  {
                      "Id":  "a6ea3449-6a85-41df-87da-2a45bff06115",
                      "Name":  "肥皂",
                      "Quantity":  5,
                      "Price":  150,
                      "IsCompleted":  false,
                      "CreatedAt":  "2025-01-21T12:49:26.6301336Z",
                      "CompletedAt":  null
                  },
                  {
                      "Id":  "eda49434-cf1f-439d-9b9c-906fa85e702d",
                      "Name":  "Rustic Wooden Gloves",
                      "Quantity":  4,
                      "Price":  69,
                      "IsCompleted":  false,
                      "CreatedAt":  "2025-01-21T12:49:26.6301617Z",
                      "CompletedAt":  null
                  },
                  {
                      "Id":  "44201875-654d-408c-a9ea-a76fb1ff1a83",
                      "Name":  "餅乾",
                      "Quantity":  4,
                      "Price":  84,
                      "IsCompleted":  true,
                      "CreatedAt":  "2025-01-21T12:49:26.6301632Z",
                      "CompletedAt":  null
                  },
                  {
                      "Id":  "56dc3030-f9ba-42f1-bde0-f1cfe7501229",
                      "Name":  "Tasty Metal Chair",
                      "Quantity":  4,
                      "Price":  353,
                      "IsCompleted":  false,
                      "CreatedAt":  "2025-01-21T12:49:26.6301696Z",
                      "CompletedAt":  null
                  },
                  {
                      "Id":  "eff8e66b-42a0-4f0a-89fa-e85191935bdd",
                      "Name":  "衛生紙",
                      "Quantity":  3,
                      "Price":  378,
                      "IsCompleted":  false,
                      "CreatedAt":  "2025-01-21T12:49:26.630173Z",
                      "CompletedAt":  null
                  },
                  {
                      "Id":  "2ec5fe01-bfc6-499a-9db1-7ff93242cc78",
                      "Name":  "魚",
                      "Quantity":  5,
                      "Price":  382,
                      "IsCompleted":  false,
                      "CreatedAt":  "2025-01-21T12:49:26.6301743Z",
                      "CompletedAt":  null
                  }
              ],
    "BuyData":  "2024-01/20"
}
