{
    "Id":  "d577f9be-6f59-498d-9de8-1d04e8feb2fc",
    "Title":  "早市採買 - 美聯社 (01/21)",
    "CreatedAt":  "2025-01-16T09:56:43.7525278+08:00",
    "Items":  [
                  {
                      "Id":  "b2567e91-f694-4023-bc8b-b6df5cb4dfbb",
                      "Name":  "原木梳子",
                      "Quantity":  5,
                      "Price":  127,
                      "IsCompleted":  true,
                      "CreatedAt":  "2025-01-15T21:43:42.8952356+08:00",
                      "CompletedAt":  "2025-01-16T08:17:31.0097095+08:00"
                  },
                  {
                      "Id":  "ab52b414-69ab-490e-9817-16c49c4a8419",
                      "Name":  "美白牙膏",
                      "Quantity":  2,
                      "Price":  157,
                      "IsCompleted":  false,
                      "CreatedAt":  "2025-01-14T18:50:57.8351725+08:00",
                      "CompletedAt":  null
                  },
                  {
                      "Id":  "2bf5ea70-a1ad-403b-99e7-e21b62a445db",
                      "Name":  "鮮榨果汁",
                      "Quantity":  3,
                      "Price":  126,
                      "IsCompleted":  true,
                      "CreatedAt":  "2025-01-19T13:52:33.9911672+08:00",
                      "CompletedAt":  "2025-01-19T21:46:59.9468667+08:00"
                  },
                  {
                      "Id":  "254ba66c-1551-4ee0-a1d6-4c8d55e7adc3",
                      "Name":  "金屬直尺",
                      "Quantity":  1,
                      "Price":  148,
                      "IsCompleted":  false,
                      "CreatedAt":  "2025-01-19T09:39:05.277615+08:00",
                      "CompletedAt":  null
                  }
              ],
    "BuyData":  "2024-01/21"
}
