{
    "Id":  "e946cdfc-d606-45e9-aa28-17b9b758b667",
    "Title":  "月底大採購 - 01/20",
    "CreatedAt":  "2025-01-19T06:57:57.4334297+08:00",
    "Items":  [
                  {
                      "Id":  "2625a053-03ea-41b5-b1aa-5b0646c36d70",
                      "Name":  "鍋子",
                      "Quantity":  3,
                      "Price":  458.99090642940590,
                      "IsCompleted":  false,
                      "CreatedAt":  "2025-01-17T02:59:29.4787514+08:00",
                      "CompletedAt":  null
                  },
                  {
                      "Id":  "c685a4f1-5ac7-469e-85df-87dce8a618a2",
                      "Name":  "運動飲料",
                      "Quantity":  10,
                      "Price":  66.931994759161970,
                      "IsCompleted":  false,
                      "CreatedAt":  "2025-01-20T00:29:23.6539103+08:00",
                      "CompletedAt":  null
                  },
                  {
                      "Id":  "0aab3372-6ed3-49f7-ad94-f8e11260fc85",
                      "Name":  "筆筒",
                      "Quantity":  5,
                      "Price":  168.387671784307140,
                      "IsCompleted":  false,
                      "CreatedAt":  "2025-01-21T05:47:58.8050548+08:00",
                      "CompletedAt":  null
                  },
                  {
                      "Id":  "4a4051fe-17e4-4e64-a7dd-a10c8de7c492",
                      "Name":  "掃把",
                      "Quantity":  6,
                      "Price":  457.092588371431030,
                      "IsCompleted":  false,
                      "CreatedAt":  "2025-01-20T14:29:15.6215355+08:00",
                      "CompletedAt":  null
                  },
                  {
                      "Id":  "6ac0d8b6-5111-4ec2-b63c-6e895ae2f293",
                      "Name":  "杯子",
                      "Quantity":  2,
                      "Price":  215.349243850797270,
                      "IsCompleted":  false,
                      "CreatedAt":  "2025-01-16T07:45:49.2735401+08:00",
                      "CompletedAt":  null
                  },
                  {
                      "Id":  "16b9dae3-8c0e-443d-8271-7fb72241a61c",
                      "Name":  "茶",
                      "Quantity":  2,
                      "Price":  96.984485560599620,
                      "IsCompleted":  false,
                      "CreatedAt":  "2025-01-20T14:37:29.0571556+08:00",
                      "CompletedAt":  null
                  }
              ],
    "BuyData":  "2024-01/20"
}
