{
    "Id":  "ff93ad3a-9348-4b76-a80e-439c6399ec42",
    "Title":  "01/21 飲料採買清單",
    "CreatedAt":  "2025-01-17T08:46:13.154065+08:00",
    "Items":  [
                  {
                      "Id":  "3f9246ec-17a1-47a5-baa1-cc8ef148dabc",
                      "Name":  "香蕉",
                      "Quantity":  3,
                      "Price":  113,
                      "IsCompleted":  false,
                      "CreatedAt":  "2025-01-21T14:31:20.672717Z",
                      "CompletedAt":  null
                  },
                  {
                      "Id":  "3b01f0f9-0ee7-479a-b0a4-bef57c3e0c42",
                      "Name":  "Unbranded Fresh Towels",
                      "Quantity":  2,
                      "Price":  233,
                      "IsCompleted":  false,
                      "CreatedAt":  "2025-01-21T14:31:20.6727458Z",
                      "CompletedAt":  null
                  },
                  {
                      "Id":  "c23e8403-5401-4774-b641-bad605e0c94f",
                      "Name":  "Tasty Wooden Soap",
                      "Quantity":  1,
                      "Price":  320,
                      "IsCompleted":  false,
                      "CreatedAt":  "2025-01-21T14:31:20.6727513Z",
                      "CompletedAt":  null
                  },
                  {
                      "Id":  "91c04e70-4525-422d-b4ac-ae9f7205ec45",
                      "Name":  "茶",
                      "Quantity":  5,
                      "Price":  251,
                      "IsCompleted":  false,
                      "CreatedAt":  "2025-01-21T14:31:20.6727536Z",
                      "CompletedAt":  null
                  },
                  {
                      "Id":  "c33abe89-b757-4f73-91be-eb90721db703",
                      "Name":  "蘋果",
                      "Quantity":  4,
                      "Price":  356,
                      "IsCompleted":  false,
                      "CreatedAt":  "2025-01-21T14:31:20.6727564Z",
                      "CompletedAt":  null
                  },
                  {
                      "Id":  "c73c9197-0d64-42e0-93e3-f2a9b1841a5b",
                      "Name":  "Tasty Fresh Pizza",
                      "Quantity":  1,
                      "Price":  281,
                      "IsCompleted":  false,
                      "CreatedAt":  "2025-01-21T14:31:20.6727631Z",
                      "CompletedAt":  null
                  },
                  {
                      "Id":  "9ef8c46c-d3c2-41bf-b469-57b22d0ed89a",
                      "Name":  "果汁",
                      "Quantity":  2,
                      "Price":  145,
                      "IsCompleted":  false,
                      "CreatedAt":  "2025-01-21T14:31:20.6727902Z",
                      "CompletedAt":  null
                  }
              ],
    "BuyData":  "2024-01/21"
}
